serf_membership
