Metadata-Version: 1.1
Name: serf-membership
Version: 1.2
Summary: This is very simple script for election a leader (primary) from all members tagged with specific role.
Home-page: https://github.com/mignev/serf-membership
Author: Marian Ignev
Author-email: m@ignev.net
License: UNKNOWN
Platform: UNKNOWN
Classifier: Development Status :: 4 - Beta
Classifier: Operating System :: POSIX
Classifier: Operating System :: POSIX :: BSD
Classifier: Operating System :: POSIX :: Linux
Classifier: Operating System :: Unix
Classifier: Programming Language :: Python
Classifier: Programming Language :: Python :: 2
Classifier: Programming Language :: Python :: 2.7
Classifier: Topic :: System :: Shells
Classifier: Topic :: Utilities
